quorum_eth_py/__init__.py
quorum_eth_py/_browser.py
quorum_eth_py/_constants.py
quorum_eth_py/_eth.py
quorum_eth_py/_gateway.py
quorum_eth_py/_http.py
quorum_eth_py/_paid_group.py
quorum_eth_py/_rum_erc20.py
quorum_eth_py/contract/PaidGroup.py
quorum_eth_py/contract/PaidGroupV2.py
quorum_eth_py/contract/RumERC20.py
quorum_eth_py/contract/__init__.py
quorum_eth_py-0.4.1.dist-info/LICENSE
quorum_eth_py-0.4.1.dist-info/METADATA
quorum_eth_py-0.4.1.dist-info/WHEEL
quorum_eth_py-0.4.1.dist-info/top_level.txt
quorum_eth_py-0.4.1.dist-info/RECORD
