Metadata-Version: 2.1
Name: quorum-eth-py
Version: 0.4.1
Summary: A python sdk for quorum-eth chain
Home-page: https://github.com/liujuanjuan1984/quorum_eth_py
Author: liujuanjuan1984
Author-email: qiaoanlu@163.com
Project-URL: Github Repo, https://github.com/liujuanjuan1984/quorum_eth_py
Project-URL: Bug Tracker, https://github.com/liujuanjuan1984/quorum_eth_py/issues
Project-URL: About Quorum, https://github.com/rumsystem/quorum
Keywords: rumsystem,quorum,eth,sdk,blockchain
Classifier: Programming Language :: Python :: 3
Classifier: Programming Language :: Python :: 3.9
Classifier: License :: OSI Approved :: MIT License
Classifier: Operating System :: OS Independent
Requires-Python: >=3.5
License-File: LICENSE
Requires-Dist: requests
Requires-Dist: web3 (==6.4.0)
